fral/__init__.py
fral/fral.py
fral/fral_ext.cpython-310-darwin.so
fral-1.0.0.dist-info/LICENSE
fral-1.0.0.dist-info/METADATA
fral-1.0.0.dist-info/WHEEL
fral-1.0.0.dist-info/top_level.txt
fral-1.0.0.dist-info/RECORD
