Metadata-Version: 2.1
Name: fral
Version: 1.0.0
Summary: Fast Random Access Log
Author: David Maaghul
Author-email: David Maaghul <test@xyz.com>
Project-URL: Homepage, https://github.com/davidmaaghul/FRAL
Classifier: License :: OSI Approved :: MIT License
Requires-Python: >=3.8
License-File: LICENSE
